libmist/__init__.py
libmist/libmist.so
libmist/extern/libboost_numpy3-py36.so.1.65.1
libmist/extern/libboost_python3-py36.so.1.65.1
libmist/extern/libboost_serialization.so.1.65.1
libmist/extern/libpython3.6m.so.1.0
libmist/extern/libstdc++.so.6
libmist/extern/libstdc++.so.6.0.25
libmist-1.3.0.dist-info/DESCRIPTION.rst
libmist-1.3.0.dist-info/METADATA
libmist-1.3.0.dist-info/RECORD
libmist-1.3.0.dist-info/WHEEL
libmist-1.3.0.dist-info/metadata.json
libmist-1.3.0.dist-info/top_level.txt
