Metadata-Version: 2.0
Name: libmist
Version: 1.3.0
Summary: Mist - Multivariable Information Theory-based relationship search tool
Home-page: https://github.com/andbanman/mist
Author: Andrew Banman
Author-email: abanman@pnri.org
License: UNKNOWN
Project-URL: Bug Tracker, https://github.com/andbanman/mist/issues
Platform: UNKNOWN
Classifier: Programming Language :: C++
Classifier: Programming Language :: Python :: 3
Classifier: License :: OSI Approved :: MIT License
Classifier: Operating System :: POSIX :: Linux
Requires-Python: >=3.6
